cal_7/__init__.py
cal_7-0.1.dist-info/METADATA
cal_7-0.1.dist-info/WHEEL
cal_7-0.1.dist-info/license.txt
cal_7-0.1.dist-info/top_level.txt
cal_7-0.1.dist-info/RECORD
