Metadata-Version: 2.1
Name: cal-7
Version: 0.1
Summary: JUST A SAMPLE FILE TO ADD TWO NUMBERS
Home-page: UNKNOWN
Author: KAILASH
Author-email: rockstarksb123@gmail.com
License: UNKNOWN
Platform: UNKNOWN
